redes_bayesianas_rey20074/__init__.py
redes_bayesianas_rey20074/bayesian_library.py
redes_bayesianas_rey20074-0.0.2.dist-info/LICENSE
redes_bayesianas_rey20074-0.0.2.dist-info/METADATA
redes_bayesianas_rey20074-0.0.2.dist-info/WHEEL
redes_bayesianas_rey20074-0.0.2.dist-info/top_level.txt
redes_bayesianas_rey20074-0.0.2.dist-info/RECORD
