Metadata-Version: 2.1
Name: redes-bayesianas-rey20074
Version: 0.0.2
Summary: Una libreria para construir redes bayesianas y realizar inferencia probabilística
Author-email: Jose Reyes <josemarianoreyesh02@gmail.com>, Esteban Aldana Reyes <example@gmail.com>, Juan Carlos Bajan <exmple@gmail.com>, Kenneth Galvez <example@gmail.com>
Project-URL: Homepage, https://github.com/JuanCarlosBajan/UVG-IA-lab2
Classifier: Programming Language :: Python :: 3
Classifier: License :: OSI Approved :: MIT License
Classifier: Operating System :: OS Independent
Requires-Python: >=3.7
License-File: LICENSE
